critical_wormhole_tools-0.3.0.dist-info/licenses/LICENSE
wh/__init__.py
wh/__main__.py
wh/cli/__init__.py
wh/cli/curl.py
wh/cli/listen.py
wh/cli/main.py
wh/cli/nc.py
wh/cli/ping.py
wh/cli/proxy.py
wh/cli/rsync.py
wh/cli/scp.py
wh/cli/serve.py
wh/cli/sftp.py
wh/cli/ssh.py
wh/cli/tunnel.py
wh/cli/wget.py
wh/core/__init__.py
wh/core/forwarder.py
wh/core/protocol.py
wh/core/transport.py
wh/core/wormhole_manager.py
wh/http/__init__.py
wh/http/client.py
wh/ssh/__init__.py
wh/ssh/client.py
wh/ssh/server.py
wh/ssh/tunnel.py
wh/transfer/__init__.py
wh/transfer/scp.py
wh/transfer/sftp.py
wh/wns/__init__.py
wh/wns/advertisement.py
wh/wns/aliases.py
wh/wns/cli.py
wh/wns/dht.py
wh/wns/discovery.py
wh/wns/identity.py
wh/wns/names.py
wh/wns/server.py
critical_wormhole_tools-0.3.0.dist-info/METADATA
critical_wormhole_tools-0.3.0.dist-info/WHEEL
critical_wormhole_tools-0.3.0.dist-info/entry_points.txt
critical_wormhole_tools-0.3.0.dist-info/top_level.txt
critical_wormhole_tools-0.3.0.dist-info/RECORD
