Metadata-Version: 2.4
Name: critical_wormhole_tools
Version: 0.3.0
Summary: Critical Wormhole Tools - Secure network utilities using Magic Wormhole code-based addressing
Author: Critical Wormhole Team
License-Expression: MIT
Project-URL: Homepage, https://github.com/bshuler/critical-wormhole-tools
Project-URL: Documentation, https://github.com/bshuler/critical-wormhole-tools#readme
Project-URL: Repository, https://github.com/bshuler/critical-wormhole-tools.git
Project-URL: Issues, https://github.com/bshuler/critical-wormhole-tools/issues
Project-URL: Changelog, https://github.com/bshuler/critical-wormhole-tools/blob/main/CHANGELOG.md
Keywords: wormhole,ssh,sftp,scp,netcat,tunnel,secure,transfer,curl,wget,magic-wormhole,p2p,peer-to-peer,encrypted,NAT-traversal
Classifier: Development Status :: 4 - Beta
Classifier: Environment :: Console
Classifier: Intended Audience :: Developers
Classifier: Intended Audience :: System Administrators
Classifier: Intended Audience :: Information Technology
Classifier: Operating System :: OS Independent
Classifier: Operating System :: POSIX :: Linux
Classifier: Operating System :: MacOS
Classifier: Operating System :: Microsoft :: Windows
Classifier: Programming Language :: Python :: 3
Classifier: Programming Language :: Python :: 3.10
Classifier: Programming Language :: Python :: 3.11
Classifier: Programming Language :: Python :: 3.12
Classifier: Programming Language :: Python :: 3.13
Classifier: Topic :: Internet
Classifier: Topic :: System :: Networking
Classifier: Topic :: Security
Classifier: Topic :: Communications :: File Sharing
Classifier: Topic :: Utilities
Requires-Python: >=3.10
License-File: LICENSE
Requires-Dist: magic-wormhole>=0.14.0
Requires-Dist: asyncssh>=2.14.0
Requires-Dist: click>=8.0.0
Requires-Dist: twisted>=22.0.0
Requires-Dist: attrs>=21.0.0
Requires-Dist: httpx>=0.25.0
Requires-Dist: rich>=13.0.0
Requires-Dist: noiseprotocol>=0.3.0
Requires-Dist: pynacl>=1.5.0
Requires-Dist: kademlia>=2.2.0
Provides-Extra: dev
Requires-Dist: pytest>=7.0.0; extra == "dev"
Requires-Dist: pytest-asyncio>=0.21.0; extra == "dev"
Requires-Dist: pytest-cov>=4.0.0; extra == "dev"
Requires-Dist: pytest-mock>=3.10.0; extra == "dev"
Requires-Dist: mypy>=1.0.0; extra == "dev"
Requires-Dist: ruff>=0.1.0; extra == "dev"
Requires-Dist: crochet>=2.0.0; extra == "dev"
Requires-Dist: build>=1.0.0; extra == "dev"
Requires-Dist: twine>=4.0.0; extra == "dev"
Dynamic: license-file
